[{"position":1,"name": "Maria","count":1105524},
{"position":2,"name": "Ana","count":931115},
{"position":3,"name": "João","count":787738},
{"position":4,"name": "Gabriel","count":577365},
{"position":5,"name": "Lucas","count":499972},
{"position":6,"name": "Pedro","count":439612},
{"position":7,"name": "Mateus","count":327290},
{"position":8,"name": "José","count":313584},
{"position":9,"name": "Gustavo","count":302475},
{"position":10,"name": "Vitória","count":282734},
{"position":11,"name": "Guilherme","count":276608},
{"position":12,"name": "Júlia","count":264647},
{"position":13,"name": "Carlos","count":264446},
{"position":14,"name": "Vítor","count":242220},
{"position":15,"name": "Felipe","count":225444},
{"position":16,"name": "Letícia","count":208527},
{"position":17,"name": "Marcos","count":199438},
{"position":18,"name": "Rafael","count":193617},
{"position":19,"name": "Luiz","count":193038},
{"position":20,"name": "Daniel","count":192619},
{"position":21,"name": "Eduardo","count":190054},
{"position":22,"name": "Matheus","count":188689},
{"position":23,"name": "Luís","count":183425},
{"position":24,"name": "Amanda","count":175868},
{"position":25,"name": "Bruno","count":174055},
{"position":26,"name": "Beatriz","count":170464},
{"position":27,"name": "Larissa","count":168755},
{"position":28,"name": "Gabriela","count":168390},
{"position":29,"name": "Paulo","count":161498},
{"position":30,"name": "Leonardo","count":147466},
{"position":31,"name": "Mariana","count":142606},
{"position":32,"name": "Vinícius","count":137930},
{"position":33,"name": "Davi","count":137796},
{"position":34,"name": "Bruna","count":137660},
{"position":35,"name": "Samuel","count":133517},
{"position":36,"name": "Victor","count":129742},
{"position":37,"name": "Camila","count":128347},
{"position":38,"name": "Isabela","count":126158},
{"position":39,"name": "Francisco","count":122915},
{"position":40,"name": "Antônio","count":122028},
{"position":41,"name": "Caio","count":122028},
{"position":42,"name": "Tiago","count":117810},
{"position":43,"name": "Luana","count":116460},
{"position":44,"name": "Sara","count":115760},
{"position":45,"name": "Eduarda","count":110144},
{"position":46,"name": "Bianca","count":108866},
{"position":47,"name": "Rafaela","count":104428},
{"position":48,"name": "Geovana","count":104253},
{"position":49,"name": "Fernanda","count":104005},
{"position":50,"name": "Igor","count":103574},
{"position":51,"name": "Natália","count":95363},
{"position":52,"name": "Laura","count":93924},
{"position":53,"name": "Luan","count":90967},
{"position":54,"name": "Juliana","count":89375},
{"position":55,"name": "André","count":89073},
{"position":56,"name": "Nícolas","count":88625},
{"position":57,"name": "Miguel","count":87764},
{"position":58,"name": "Nicole","count":86466},
{"position":59,"name": "Thiago","count":85533},
{"position":60,"name": "Gabriele","count":84726},
{"position":61,"name": "Yasmin","count":84675},
{"position":62,"name": "Arthur","count":83840},
{"position":63,"name": "Henrique","count":83111},
{"position":64,"name": "Cauã","count":82191},
{"position":65,"name": "Rodrigo","count":81604},
{"position":66,"name": "Raissa","count":80396},
{"position":67,"name": "Sabrina","count":80087},
{"position":68,"name": "Diego","count":79767},
{"position":69,"name": "Lívia","count":78342},
{"position":70,"name": "Lara","count":78225},
{"position":71,"name": "Artur","count":77813},
{"position":72,"name": "Ruan","count":77308},
{"position":73,"name": "Aline","count":74973},
{"position":74,"name": "Milena","count":74238},
{"position":75,"name": "Rian","count":71273},
{"position":76,"name": "Giovana","count":70348},
{"position":77,"name": "Jéssica","count":67406},
{"position":78,"name": "Brenda","count":67036},
{"position":79,"name": "Vanessa","count":66381},
{"position":80,"name": "Kauan","count":66119},
{"position":81,"name": "Débora","count":65661},
{"position":82,"name": "David","count":63869},
{"position":83,"name": "Anderson","count":62810},
{"position":84,"name": "Caroline","count":62660},
{"position":85,"name": "Breno","count":62305},
{"position":86,"name": "Renan","count":62105},
{"position":87,"name": "Marcelo","count":61984},
{"position":88,"name": "Leandro","count":61127},
{"position":89,"name": "Alice","count":61038},
{"position":90,"name": "Fernando","count":60566},
{"position":91,"name": "Sofia","count":59560},
{"position":92,"name": "Luiza","count":58458},
{"position":93,"name": "Luíza","count":58458},
{"position":94,"name": "Andressa","count":57984},
{"position":95,"name": "Alan","count":57730},
{"position":96,"name": "Isadora","count":57657},
{"position":97,"name": "Júlio","count":56456},
{"position":98,"name": "Diogo","count":56387},
{"position":99,"name": "Tainá","count":56136},
{"position":100,"name": "Rebeca","count":56020},
{"position":101,"name": "Kauã","count":55765},
{"position":102,"name": "Murilo","count":55282},
{"position":103,"name": "Alexandre","count":54296},
{"position":104,"name": "Danilo","count":53911},
{"position":105,"name": "Douglas","count":53627},
{"position":106,"name": "Érica","count":53494},
{"position":107,"name": "Wesley","count":52520},
{"position":108,"name": "Taís","count":51509},
{"position":109,"name": "Emily","count":51339},
{"position":110,"name": "Carla","count":50889},
{"position":111,"name": "Vinícios","count":50536},
{"position":112,"name": "Isabele","count":50387},
{"position":113,"name": "Raiane","count":50327},
{"position":114,"name": "Alex","count":50250},
{"position":115,"name": "Raquel","count":48522},
{"position":116,"name": "Ricardo","count":48431},
{"position":117,"name": "Fábio","count":48117},
{"position":118,"name": "Lais","count":47599},
{"position":119,"name": "Ítalo","count":47453},
{"position":120,"name": "Bárbara","count":46210},
{"position":121,"name": "Tainara","count":46209},
{"position":122,"name": "Clara","count":45297},
{"position":123,"name": "Talita","count":44970},
{"position":124,"name": "Jenifer","count":44685},
{"position":125,"name": "Carolina","count":44647},
{"position":126,"name": "Lorena","count":44538},
{"position":127,"name": "Pamela","count":43954},
{"position":128,"name": "Cauan","count":43913},
{"position":129,"name": "Enzo","count":43584},
{"position":130,"name": "Fabrício","count":43466},
{"position":131,"name": "Samara","count":42619},
{"position":132,"name": "Ester","count":42394},
{"position":133,"name": "Evelin","count":41736},
{"position":134,"name": "Iago","count":41372},
{"position":135,"name": "Ingrid","count":41046},
{"position":136,"name": "Daniela","count":39319},
{"position":137,"name": "Yuri","count":39316},
{"position":138,"name": "Erick","count":39076},
{"position":139,"name": "Tamires","count":38963},
{"position":140,"name": "Marina","count":38844},
{"position":141,"name": "Jaqueline","count":38245},
{"position":142,"name": "Iasmin","count":37949},
{"position":143,"name": "Eric","count":37926},
{"position":144,"name": "Maicon","count":37376},
{"position":145,"name": "Flávia","count":36435},
{"position":146,"name": "Natan","count":35211},
{"position":147,"name": "Marcela","count":35165},
{"position":148,"name": "Thais","count":35100},
{"position":149,"name": "Thaís","count":35100},
{"position":150,"name": "Renata","count":34894},
{"position":151,"name": "Alana","count":34792},
{"position":152,"name": "Everton","count":33573},
{"position":153,"name": "Adriele","count":32859},
{"position":154,"name": "Emerson","count":32647},
{"position":155,"name": "Ryan","count":32300},
{"position":156,"name": "Caíque","count":31836},
{"position":157,"name": "Manuela","count":31790},
{"position":158,"name": "Emanuel","count":31605},
{"position":159,"name": "Maiara","count":31274},
{"position":160,"name": "Kaique","count":31086},
{"position":161,"name": "Francisca","count":30991},
{"position":162,"name": "Jamile","count":30986},
{"position":163,"name": "Joice","count":30837},
{"position":164,"name": "Antônia","count":30713},
{"position":165,"name": "Willian","count":29701},
{"position":166,"name": "Alessandra","count":29496},
{"position":167,"name": "Victória","count":29390},
{"position":168,"name": "Adriano","count":29329},
{"position":169,"name": "Paula","count":29206},
{"position":170,"name": "Alison","count":28571},
{"position":171,"name": "Hugo","count":28296},
{"position":172,"name": "Juan","count":28094},
{"position":173,"name": "Emilly","count":27748},
{"position":174,"name": "Renato","count":27456},
{"position":175,"name": "Flávio","count":27446},
{"position":176,"name": "Bernardo","count":27016},
{"position":177,"name": "Jonas","count":27015},
{"position":178,"name": "Gisele","count":26970},
{"position":179,"name": "Patrícia","count":26954},
{"position":180,"name": "Giovanna","count":26784},
{"position":181,"name": "Michele","count":26518},
{"position":182,"name": "Luciano","count":26224},
{"position":183,"name": "Anna","count":26129},
{"position":184,"name": "Richard","count":26101},
{"position":185,"name": "Melissa","count":25951},
{"position":186,"name": "Elen","count":25849},
{"position":187,"name": "Márcio","count":25792},
{"position":188,"name": "Jorge","count":25415},
{"position":189,"name": "Marco","count":25240},
{"position":190,"name": "Adrian","count":25213},
{"position":191,"name": "Erik","count":24372},
{"position":192,"name": "Franciele","count":24363},
{"position":193,"name": "Eloísa","count":24303},
{"position":194,"name": "Viviane","count":24299},
{"position":195,"name": "Ian","count":24114},
{"position":196,"name": "Paola","count":24090},
{"position":197,"name": "Kaio","count":23889},
{"position":198,"name": "Kevin","count":23873},
{"position":199,"name": "Samira","count":23595},
{"position":200,"name": "Maisa","count":23509}]