[{"position":1,"name": "Sarah","count":19984},
{"position":2,"name": "Karen","count":13524},
{"position":3,"name": "Emma","count":13477},
{"position":4,"name": "Jessica","count":13079},
{"position":5,"name": "Michelle","count":12961},
{"position":6,"name": "Susan","count":12686},
{"position":7,"name": "Elizabeth","count":11996},
{"position":8,"name": "Lisa","count":11891},
{"position":9,"name": "Rebecca","count":11608},
{"position":10,"name": "Christine","count":10604},
{"position":11,"name": "Nicola","count":10395},
{"position":12,"name": "Jennifer","count":9991},
{"position":13,"name": "Rachel","count":9769},
{"position":14,"name": "Angela","count":9634},
{"position":15,"name": "Anna","count":9465},
{"position":16,"name": "Joanne","count":9329},
{"position":17,"name": "Olivia","count":9252},
{"position":18,"name": "Hannah","count":9242},
{"position":19,"name": "Deborah","count":8819},
{"position":20,"name": "Julie","count":8289},
{"position":21,"name": "Charlotte","count":8240},
{"position":22,"name": "Sophie","count":8220},
{"position":23,"name": "Emily","count":8126},
{"position":24,"name": "Helen","count":7775},
{"position":25,"name": "Catherine","count":7765},
{"position":26,"name": "Amanda","count":7667},
{"position":27,"name": "Samantha","count":7549},
{"position":28,"name": "Sandra","count":7429},
{"position":29,"name": "Sharon","count":7243},
{"position":30,"name": "Amy","count":7061},
{"position":31,"name": "Donna","count":7054},
{"position":32,"name": "Tracey","count":6914},
{"position":33,"name": "Melissa","count":6898},
{"position":34,"name": "Tania","count":6879},
{"position":35,"name": "Wendy","count":6832},
{"position":36,"name": "Grace","count":6381},
{"position":37,"name": "Linda","count":6288},
{"position":38,"name": "Kelly","count":6137},
{"position":39,"name": "Fiona","count":6039},
{"position":40,"name": "Nicole","count":6011},
{"position":41,"name": "Mary","count":5891},
{"position":42,"name": "Georgia","count":5885},
{"position":43,"name": "Megan","count":5869},
{"position":44,"name": "Stephanie","count":5794},
{"position":45,"name": "Kate","count":5782},
{"position":46,"name": "Ella","count":5672},
{"position":47,"name": "Kim","count":5667},
{"position":48,"name": "Robyn","count":5598},
{"position":49,"name": "Jacqueline","count":5559},
{"position":50,"name": "Maria","count":5541},
{"position":51,"name": "Natasha","count":5533},
{"position":52,"name": "Margaret","count":5517},
{"position":53,"name": "Lucy","count":5251},
{"position":54,"name": "Kathryn","count":5104},
{"position":55,"name": "Patricia","count":5007},
{"position":56,"name": "Andrea","count":5003},
{"position":57,"name": "Hayley","count":4951},
{"position":58,"name": "Jane","count":4932},
{"position":59,"name": "Victoria","count":4911},
{"position":60,"name": "Chloe","count":4882},
{"position":61,"name": "Suzanne","count":4705},
{"position":62,"name": "Ruby","count":4681},
{"position":63,"name": "Judith","count":4677},
{"position":64,"name": "Laura","count":4669},
{"position":65,"name": "Isabella","count":4619},
{"position":66,"name": "Louise","count":4580},
{"position":67,"name": "Amelia","count":4520},
{"position":68,"name": "Melanie","count":4476},
{"position":69,"name": "Holly","count":4453},
{"position":70,"name": "Heather","count":4351},
{"position":71,"name": "Zoe","count":4301},
{"position":72,"name": "Danielle","count":4151},
{"position":73,"name": "Natalie","count":4112},
{"position":74,"name": "Tracy","count":3999},
{"position":75,"name": "Diane","count":3952},
{"position":76,"name": "Vanessa","count":3941},
{"position":77,"name": "Katherine","count":3912},
{"position":78,"name": "Jasmine","count":3888},
{"position":79,"name": "Anne","count":3879},
{"position":80,"name": "Lily","count":3844},
{"position":81,"name": "Paige","count":3766},
{"position":82,"name": "Amber","count":3764},
{"position":83,"name": "Kylie","count":3692},
{"position":84,"name": "Paula","count":3667},
{"position":85,"name": "Lynette","count":3666},
{"position":86,"name": "Brooke","count":3634},
{"position":87,"name": "Carol","count":3626},
{"position":88,"name": "Denise","count":3577},
{"position":89,"name": "Barbara","count":3531},
{"position":90,"name": "Leanne","count":3478},
{"position":91,"name": "Katie","count":3455},
{"position":92,"name": "Alison","count":3444},
{"position":93,"name": "Alice","count":3426},
{"position":94,"name": "Renee","count":3387},
{"position":95,"name": "Caitlin","count":3370},
{"position":96,"name": "Lauren","count":3275},
{"position":97,"name": "Madison","count":3249},
{"position":98,"name": "Jade","count":3234},
{"position":99,"name": "Carolyn","count":3212},
{"position":100,"name": "Rachael","count":3210},
{"position":101,"name": "Katrina","count":3184},
{"position":102,"name": "Claire","count":3174},
{"position":103,"name": "Vicki","count":3171},
{"position":104,"name": "Ashleigh","count":3158},
{"position":105,"name": "Debra","count":3094},
{"position":106,"name": "Raewyn","count":3039},
{"position":107,"name": "Stacey","count":3037},
{"position":108,"name": "Mia","count":2974},
{"position":109,"name": "Courtney","count":2941},
{"position":110,"name": "Sophia","count":2887},
{"position":111,"name": "Ava","count":2852},
{"position":112,"name": "Kayla","count":2806},
{"position":113,"name": "Joanna","count":2716},
{"position":114,"name": "Isla","count":2707},
{"position":115,"name": "Alexandra","count":2689},
{"position":116,"name": "Pamela","count":2677},
{"position":117,"name": "Christina","count":2675},
{"position":118,"name": "Janine","count":2641},
{"position":119,"name": "Marie","count":2582},
{"position":120,"name": "Toni","count":2572},
{"position":121,"name": "Shelley","count":2569},
{"position":122,"name": "Caroline","count":2530},
{"position":123,"name": "Kathleen","count":2503},
{"position":124,"name": "Ashley","count":2477},
{"position":125,"name": "Brenda","count":2451},
{"position":126,"name": "Shannon","count":2446},
{"position":127,"name": "Sally","count":2445},
{"position":128,"name": "Bronwyn","count":2406},
{"position":129,"name": "Pauline","count":2404},
{"position":130,"name": "Annette","count":2348},
{"position":131,"name": "Aimee","count":2315},
{"position":132,"name": "Dianne","count":2314},
{"position":133,"name": "Teresa","count":2294},
{"position":134,"name": "Maree","count":2270},
{"position":135,"name": "Janet","count":2253},
{"position":136,"name": "Abigail","count":2200},
{"position":137,"name": "Tina","count":2124},
{"position":138,"name": "Gemma","count":2120},
{"position":139,"name": "Maia","count":2106},
{"position":140,"name": "Julia","count":2092},
{"position":141,"name": "Rochelle","count":2086},
{"position":142,"name": "Kirsty","count":2083},
{"position":143,"name": "Maddison","count":1995},
{"position":144,"name": "Leah","count":1992},
{"position":145,"name": "Lynda","count":1972},
{"position":146,"name": "Chelsea","count":1943},
{"position":147,"name": "Rosemary","count":1918},
{"position":148,"name": "Kerry","count":1917},
{"position":149,"name": "Janice","count":1881},
{"position":150,"name": "Monique","count":1859},
{"position":151,"name": "Ann","count":1834},
{"position":152,"name": "Tayla","count":1823},
{"position":153,"name": "Yvonne","count":1822},
{"position":154,"name": "Eva","count":1813},
{"position":155,"name": "Cheryl","count":1781},
{"position":156,"name": "Eden","count":1721},
{"position":157,"name": "Sheryl","count":1688},
{"position":158,"name": "Lorraine","count":1675},
{"position":159,"name": "Shirley","count":1673},
{"position":160,"name": "Erin","count":1624},
{"position":161,"name": "Ruth","count":1616},
{"position":162,"name": "Bridget","count":1611},
{"position":163,"name": "Tanya","count":1595},
{"position":164,"name": "Molly","count":1590},
{"position":165,"name": "Jan","count":1587},
{"position":166,"name": "Summer","count":1579},
{"position":167,"name": "Kimberley","count":1578},
{"position":168,"name": "Jillian","count":1571},
{"position":169,"name": "Harper","count":1567},
{"position":170,"name": "Anita","count":1526},
{"position":171,"name": "Sienna","count":1518},
{"position":172,"name": "Phoebe","count":1503},
{"position":173,"name": "Taylor","count":1499},
{"position":174,"name": "Mila","count":1493},
{"position":175,"name": "Mikayla","count":1492},
{"position":176,"name": "Rose","count":1479},
{"position":177,"name": "Stella","count":1469},
{"position":178,"name": "Zara","count":1457},
{"position":179,"name": "Lesley","count":1453},
{"position":180,"name": "Tessa","count":1439},
{"position":181,"name": "Bella","count":1395},
{"position":182,"name": "Debbie","count":1389},
{"position":183,"name": "Gillian","count":1388},
{"position":184,"name": "Colleen","count":1367},
{"position":185,"name": "Philippa","count":1359},
{"position":186,"name": "Isabelle","count":1357},
{"position":187,"name": "Penelope","count":1344},
{"position":188,"name": "Aria","count":1327},
{"position":189,"name": "Mackenzie","count":1282},
{"position":190,"name": "Nikita","count":1263},
{"position":191,"name": "Rebekah","count":1255},
{"position":192,"name": "Belinda","count":1254},
{"position":193,"name": "Gail","count":1253},
{"position":194,"name": "Brittany","count":1239},
{"position":195,"name": "Scarlett","count":1232},
{"position":196,"name": "Frances","count":1212},
{"position":197,"name": "Shona","count":1210},
{"position":198,"name": "Kay","count":1205},
{"position":199,"name": "Alana","count":1194},
{"position":200,"name": "Kirsten","count":1183}]